pyportscanner/PortScanner.py
pyportscanner/__init__.py
pyportscanner/pyscanner.py
pyportscanner/etc/__init__.py
pyportscanner/etc/helper.py
pyportscanner/etc/nmap-services.dat
pyportscanner/etc/service_port.py
tests/__init__.py
tests/test_helper.py
tests/test_pyscanner.py
pyportscanner-0.3.2.dist-info/LICENSE
pyportscanner-0.3.2.dist-info/METADATA
pyportscanner-0.3.2.dist-info/WHEEL
pyportscanner-0.3.2.dist-info/top_level.txt
pyportscanner-0.3.2.dist-info/RECORD
